<?xml version="1.0" encoding="utf-8"?>
<!DOCTYPE install PUBLIC "-//Joomla! 2.5//DTD template 1.0//EN" "http://www.joomla.org/xml/dtd/2.5/template-install.dtd">

<extension version="2.5" type="template" client="site" method="upgrade">

	<name>Inquire</name>
	<creationDate>2014-07-01</creationDate>
	<author>Matt Weaver</author>
	<copyright>Copyright © Inquire www.inquire.org.uk</copyright>
	<authorEmail>admin@inqiure.org.uk</authorEmail>
	<authorUrl>http://www.inquire.org.uk</authorUrl>
	<version>1.0.0</version>
	<description>Inquire UK Frontend Template</description>

	<files>
		<folder>css</folder>
		<folder>html</folder>
		<folder>images</folder>
		<folder>js</folder>
		<filename>component.php</filename>
		<filename>error.php</filename>
		<filename>index.php</filename>
		<filename>offline.php</filename>
		<filename>template_preview.png</filename>
		<filename>template_thumbnail.png</filename>
		<filename>favicon.ico</filename>
		<filename>templateDetails.xml</filename>
	</files>

	<positions><!-- define the positions for modules here -->
		<position>menu</position>
		<position>top-left</position>
		<position>top-right</position>
		<position>promos</position>
		<position>main</position>
		<position>footer</position>
		<position>debug</position>
	</positions>
</extension>
